deeplcretrainer/__init__.py
deeplcretrainer/cnn_functions.py
deeplcretrainer/deeplcretrainer.py
deeplcretrainer-1.0.2.dist-info/LICENSE
deeplcretrainer-1.0.2.dist-info/WHEEL
deeplcretrainer-1.0.2.dist-info/METADATA
deeplcretrainer-1.0.2.dist-info/RECORD
